delpinos/crud/core/application/encoders/base_encoder.py
delpinos/crud/core/application/events/base_event.py
delpinos/crud/core/application/integrations/api_integration.py
delpinos/crud/core/application/integrations/base_integration.py
delpinos/crud/core/application/repositories/base_repository.py
delpinos/crud/core/application/services/base_service.py
delpinos/crud/core/application/validators/base_validator.py
delpinos/crud/core/domain/entities/__init__.py
delpinos/crud/core/domain/entities/api_integration_entity.py
delpinos/crud/core/domain/entities/field_schema_entity.py
delpinos/crud/core/domain/entities/field_value_entity.py
delpinos/crud/core/domain/entities/filter_entity.py
delpinos/crud/core/domain/entities/filter_field_entity.py
delpinos/crud/core/domain/entities/filter_sort_pagination_entity.py
delpinos/crud/core/domain/entities/pagination_entity.py
delpinos/crud/core/domain/entities/security_token_entity.py
delpinos/crud/core/domain/entities/sort_field_entity.py
delpinos/crud/core/domain/entities/trigger_entity.py
delpinos/crud/core/domain/enums/entities/schema_entities_enum.py
delpinos/crud/core/domain/enums/exceptions/api_integration_exceptions_enum.py
delpinos/crud/core/domain/enums/exceptions/persistence_exceptions_enum.py
delpinos/crud/core/domain/events/base_event_abstract.py
delpinos/crud/core/domain/exceptions/api_integration_exception.py
delpinos/crud/core/domain/integrations/api_integration_abstract.py
delpinos/crud/core/domain/integrations/base_integration_abstract.py
delpinos/crud/core/domain/repositories/base_repository_abstract.py
delpinos/crud/core/domain/services/base_service_abstract.py
delpinos/crud/core/domain/validators/base_validator_abstract.py
delpinos_crud_core-0.0.1.dev1.dist-info/METADATA
delpinos_crud_core-0.0.1.dev1.dist-info/WHEEL
delpinos_crud_core-0.0.1.dev1.dist-info/top_level.txt
delpinos_crud_core-0.0.1.dev1.dist-info/RECORD
