Metadata-Version: 2.1
Name: delpinos-crud-core
Version: 0.0.1.dev1
Summary: Delpinos Crud Core - Delpinos Softwares
Author-email: Alef Bruno Delpino de Oliveira <alef@delpinos.com>
Keywords: delpinos,crud,core
Classifier: Programming Language :: Python :: 3
Classifier: Programming Language :: Python :: 3.10
Classifier: Topic :: Software Development :: Libraries :: Python Modules
Requires-Python: >=3.10
Requires-Dist: delpinos-core >=0.0.1.dev3
